nestingnote/__init__.py
nestingnote/__main__.py
nestingnote/column.py
nestingnote/commands.py
nestingnote/controller.py
nestingnote/directions.py
nestingnote/find_key.py
nestingnote/key.py
nestingnote/linuxView.py
nestingnote/model.py
nestingnote/nestedlist.py
nestingnote/oneTimeBanner.py
nestingnote/row.py
nestingnote/simpleNestedList.py
nestingnote/styles.py
nestingnote/testView.py
nestingnote/test_model.py
nestingnote/test_nestedlist.py
nestingnote/test_row.py
nestingnote/view.py
nestingnote-0.0.11.dist-info/LICENSE
nestingnote-0.0.11.dist-info/METADATA
nestingnote-0.0.11.dist-info/WHEEL
nestingnote-0.0.11.dist-info/top_level.txt
nestingnote-0.0.11.dist-info/RECORD
