Metadata-Version: 2.1
Name: nestingnote
Version: 0.0.11
Summary: Terminal note-taking application
Home-page: https://github.com/woodsonmiles/nesting-note
Author: Woodson Miles
Author-email: woodomiles@gmail.com
License: UNKNOWN
Platform: UNKNOWN
Classifier: Programming Language :: Python :: 3
Classifier: License :: OSI Approved :: MIT License
Classifier: Operating System :: OS Independent
Requires-Python: >3.6
Requires-Dist: windows-curses (==2.1.0) ; platform_system == "Windows"
